{
  "XMLHeader":
  {
    "version" : "1.0",
    "encoding" : "UTF-8"
  },
  "XMLEnclosureTag" : "PAYMENTACH",
  "Fields" :
  [
    {
      "name":"ORDERID",
      "type":"text",
      "maxlenght":12,
      "required":true,
      "form":false
    },
    {
      "name":"TERMINALID",
      "type":"number",
      "required":true,
      "form":false
    },
    {
      "name":"AMOUNT",
      "type":"number",
      "required":true,
      "form":false
    },
    {
      "name":"CURRENCY",
      "type":"text",
      "minlenght":3,
      "maxlenght":3,
      "required":true,
      "form":false
    },
    {
      "name":"DATETIME",
      "type":"datetime",
      "required":true,
      "format":"Y-m-dH:i:s:u",
      "form":false
    },
    {
      "name":"TERMINALTYPE",
      "type":"number",
      "minlenght":1,
      "maxlenght":1,
      "required":true,
      "form":false,
      "options":"1 => MOTO (Mail Order/Telephone Order) / 2 => eCommerce"
    },
    {
      "name":"ACH_SECURE",
      "type":"text",
      "minlenght":1,
      "maxlenght":1,
      "required":false,
      "form":false
    },
    {
      "name":"ACCOUNT_TYPE",
      "type":"text",
      "required":true,
      "form":false,
      "options":"CHECKING => checking / SAVINGS => savings"
    },
    {
      "name":"ACCOUNT_NUMBER",
      "type":"number",
      "required":true,
      "form":false
    },
    {
      "name":"ROUTING_NUMBER",
      "type":"number",
      "required":true,
      "form":false
    },
    {
      "name":"ACCOUNT_NAME",
      "type":"text",
      "required":true,
      "form":false
    },
    {
      "name":"CHECK_NUMBER",
      "type":"number",
      "required":false,
      "form":false
    },
    {
      "name":"ADDRESS1",
      "type":"text",
      "required":false,
      "form":true
    },
    {
      "name":"ADDRESS2",
      "type":"text",
      "required":false,
      "form":true
    },
    {
      "name":"CITY",
      "type":"text",
      "required":false,
      "form":true
    },
    {
      "name":"REGION",
      "type":"text",
      "required":false,
      "form":true
    },
    {
      "name":"POSTCODE",
      "type":"text",
      "required":false,
      "form":true
    },
    {
      "name":"COUNTRY",
      "type":"text",
      "required":false,
      "form":true
    },
    {
      "name":"PHONE",
      "type":"text",
      "required":false,
      "form":false
    },
    {
      "name":"IPADDRESS",
      "type":"text",
      "required":false,
      "form":false
    },
    {
      "name":"EMAIL",
      "type":"text",
      "required":false,
      "form":true
    },
    {
      "name":"DESCRIPTION",
      "type":"text",
      "required":false,
      "form":false
    },
    {
      "name":"DL_STATE",
      "type":"text",
      "minlenght":2,
      "maxlenght":2,
      "required":false,
      "form":false
    },
    {
      "name":"DL_NUMBER",
      "type":"number",
      "minlenght":2,
      "maxlenght":2,
      "required":false,
      "form":false
    },

    {
      "name":"HASH",
      "type":"text",
      "required":true,
      "form":false
    }
  ]
}
